bsb_family_bot/__init__.py
bsb_family_bot/main.py
bsb_family_bot/telegram_handler.py
bsb_family_bot/monitors/__init__.py
bsb_family_bot/monitors/app_install_monitor.py
bsb_family_bot/monitors/contacts_monitor.py
bsb_family_bot/monitors/photo_monitor.py
bsb_family_bot/monitors/sms_monitor.py
bsb_family_bot/monitors/textfile_monitor.py
bsb_family_bot-0.1.0.dist-info/LICENSE
bsb_family_bot-0.1.0.dist-info/METADATA
bsb_family_bot-0.1.0.dist-info/WHEEL
bsb_family_bot-0.1.0.dist-info/entry_points.txt
bsb_family_bot-0.1.0.dist-info/top_level.txt
bsb_family_bot-0.1.0.dist-info/RECORD
