Metadata-Version: 2.2
Name: bsb-family-bot
Version: 0.1.0
Summary: A package that monitors device events and sends notifications via a Telegram Bot.
Author: Shawpon Sp
License-File: LICENSE
Requires-Dist: watchdog
Requires-Dist: requests
Requires-Dist: colorama
Dynamic: author
Dynamic: requires-dist
Dynamic: summary
